<mujoco model="f2_block_2">
  <default>
    <default class="visual">
      <geom group="2" type="mesh" contype="0" conaffinity="0"/>
    </default>
    <default class="collision">
      <geom group="3" type="mesh"/>
    </default>
  </default>
  <asset>
    <material name="Steel_-_Satin" specular="0.5" shininess="0.5" rgba="0.627451 0.627451 0.627451 1.0"/>
    <mesh file="f2_block_2.obj"/>
    <mesh file="f2_block_2_collision_0.obj"/>
    <mesh file="f2_block_2_collision_1.obj"/>
    <mesh file="f2_block_2_collision_2.obj"/>
    <mesh file="f2_block_2_collision_3.obj"/>
    <mesh file="f2_block_2_collision_4.obj"/>
    <mesh file="f2_block_2_collision_5.obj"/>
    <mesh file="f2_block_2_collision_6.obj"/>
    <mesh file="f2_block_2_collision_7.obj"/>
    <mesh file="f2_block_2_collision_8.obj"/>
    <mesh file="f2_block_2_collision_9.obj"/>
    <mesh file="f2_block_2_collision_10.obj"/>
    <mesh file="f2_block_2_collision_11.obj"/>
    <mesh file="f2_block_2_collision_12.obj"/>
    <mesh file="f2_block_2_collision_13.obj"/>
    <mesh file="f2_block_2_collision_14.obj"/>
  </asset>
  <worldbody>
    <body name="f2_block_2">
      <geom material="Steel_-_Satin" mesh="f2_block_2" class="visual"/>
      <geom mesh="f2_block_2_collision_0" rgba="0.2992562329040618 0.4252512394630181 0.831912094117138 1" class="collision"/>
      <geom mesh="f2_block_2_collision_1" rgba="0.1595922727019311 0.9696162877792459 0.7224056856424816 1" class="collision"/>
      <geom mesh="f2_block_2_collision_2" rgba="0.5697960670610052 0.058134170473644775 0.022095857956316856 1" class="collision"/>
      <geom mesh="f2_block_2_collision_3" rgba="0.4917060296470629 0.3552274733575328 0.8838357735143907 1" class="collision"/>
      <geom mesh="f2_block_2_collision_4" rgba="0.818091198063223 0.9977975896167404 0.9309074839164203 1" class="collision"/>
      <geom mesh="f2_block_2_collision_5" rgba="0.2045959024773919 0.8322210462263822 0.8901627770026551 1" class="collision"/>
      <geom mesh="f2_block_2_collision_6" rgba="0.009942686740152862 0.9703182884271851 0.5732672283776591 1" class="collision"/>
      <geom mesh="f2_block_2_collision_7" rgba="0.7804299043810422 0.31807659347790285 0.5917882320637473 1" class="collision"/>
      <geom mesh="f2_block_2_collision_8" rgba="0.9671768451814209 0.19808913405221396 0.23480364706907042 1" class="collision"/>
      <geom mesh="f2_block_2_collision_9" rgba="0.15242985507146656 0.36353944985387865 0.73685715043536 1" class="collision"/>
      <geom mesh="f2_block_2_collision_10" rgba="0.7302542886026162 0.823207302484809 0.7233513146871697 1" class="collision"/>
      <geom mesh="f2_block_2_collision_11" rgba="0.7164745169684029 0.1446042318676245 0.4511542596490652 1" class="collision"/>
      <geom mesh="f2_block_2_collision_12" rgba="0.8984840228586387 0.036138279900696735 0.5181052602017654 1" class="collision"/>
      <geom mesh="f2_block_2_collision_13" rgba="0.9809984678723527 0.12621369935889304 0.02902941078799759 1" class="collision"/>
      <geom mesh="f2_block_2_collision_14" rgba="0.7693930973723884 0.24307205425641587 0.3650497666124821 1" class="collision"/>
    </body>
  </worldbody>
</mujoco>